{
  "generated_at": "2026-04-03 11:26:03",
  "update_status": "【暫定評価】（枠順確定・オッズ未反映）",
  "races": [
    {
      "race_id": "202606030311",
      "race_name": "ダービー卿CT(G3)",
      "is_graded": true,
      "place": "中山",
      "round": 11,
      "top_pickup": {
        "horse_number": 1,
        "horse_name": "ゾンニッヒ",
        "jockey_name": "団野",
        "popularity": 10,
        "odds": 9.9,
        "features_raw": {
          "umaban": 1.0,
          "wakuban": 1.0,
          "weight_carried": 57.5,
          "horse_weight": 480.0,
          "weight_change": 0.0,
          "age": 8.0,
          "time_index": 49.0,
          "last_3f_index": 49.5,
          "pedigree_index": 24.0,
          "affinity_index": 20.0
        },
        "win_prob": 0.1,
        "place_prob": 0.1,
        "expectancy_score": 0.01,
        "miaomi_score": 1.0,
        "is_value": false,
        "reasoning": "ゾンニッヒ: 時計面で若干の不安要素あり / 団野騎手とのコンビネーションに注目 / 直近の仕上がりは安定"
      },
      "axis_pickup": {
        "horse_number": 2,
        "horse_name": "ミニトランザット",
        "jockey_name": "西村淳",
        "popularity": 10,
        "odds": 9.9,
        "features_raw": {
          "umaban": 2.0,
          "wakuban": 1.0,
          "weight_carried": 56.0,
          "horse_weight": 480.0,
          "weight_change": 0.0,
          "age": 4.0,
          "time_index": 45.0,
          "last_3f_index": 47.5,
          "pedigree_index": 20.0,
          "affinity_index": 22.0
        },
        "win_prob": 0.1,
        "place_prob": 0.1,
        "expectancy_score": 0.01,
        "miaomi_score": 1.0,
        "is_value": false,
        "reasoning": "ミニトランザット: 時計面で若干の不安要素あり / 西村淳騎手とのコンビネーションに注目 / 直近の仕上がりは安定"
      },
      "darkhorse_pickup": {
        "horse_number": 4,
        "horse_name": "メタルスピード",
        "jockey_name": "岩田康",
        "popularity": 10,
        "odds": 9.9,
        "features_raw": {
          "umaban": 4.0,
          "wakuban": 2.0,
          "weight_carried": 55.0,
          "horse_weight": 480.0,
          "weight_change": 0.0,
          "age": 6.0,
          "time_index": 52.0,
          "last_3f_index": 51.0,
          "pedigree_index": 22.0,
          "affinity_index": 26.0
        },
        "win_prob": 0.1,
        "place_prob": 0.1,
        "expectancy_score": 0.01,
        "miaomi_score": 1.0,
        "is_value": false,
        "reasoning": "メタルスピード: 時計面で若干の不安要素あり / 岩田康騎手とのコンビネーションに注目 / 直近の仕上がりは安定"
      },
      "recommended_bet": "馬連 1 - 2 / ワイド 2 - 4",
      "all_horses": [
        {
          "horse_number": 1,
          "horse_name": "ゾンニッヒ",
          "jockey_name": "団野",
          "popularity": 10,
          "odds": 9.9,
          "win_prob": 0.1,
          "place_prob": 0.1,
          "expectancy_score": 0.01,
          "miaomi_score": 1.0,
          "is_value": false,
          "reasoning": "ゾンニッヒ: 時計面で若干の不安要素あり / 団野騎手とのコンビネーションに注目 / 直近の仕上がりは安定"
        },
        {
          "horse_number": 2,
          "horse_name": "ミニトランザット",
          "jockey_name": "西村淳",
          "popularity": 10,
          "odds": 9.9,
          "win_prob": 0.1,
          "place_prob": 0.1,
          "expectancy_score": 0.01,
          "miaomi_score": 1.0,
          "is_value": false,
          "reasoning": "ミニトランザット: 時計面で若干の不安要素あり / 西村淳騎手とのコンビネーションに注目 / 直近の仕上がりは安定"
        },
        {
          "horse_number": 4,
          "horse_name": "メタルスピード",
          "jockey_name": "岩田康",
          "popularity": 10,
          "odds": 9.9,
          "win_prob": 0.1,
          "place_prob": 0.1,
          "expectancy_score": 0.01,
          "miaomi_score": 1.0,
          "is_value": false,
          "reasoning": "メタルスピード: 時計面で若干の不安要素あり / 岩田康騎手とのコンビネーションに注目 / 直近の仕上がりは安定"
        },
        {
          "horse_number": 6,
          "horse_name": "マテンロウオリオン",
          "jockey_name": "横山典",
          "popularity": 10,
          "odds": 9.9,
          "win_prob": 0.1,
          "place_prob": 0.1,
          "expectancy_score": 0.01,
          "miaomi_score": 1.0,
          "is_value": false,
          "reasoning": "マテンロウオリオン: 時計面で若干の不安要素あり / 横山典騎手とのコンビネーションに注目 / 直近の仕上がりは安定"
        },
        {
          "horse_number": 8,
          "horse_name": "ファーヴェント",
          "jockey_name": "横山武",
          "popularity": 10,
          "odds": 9.9,
          "win_prob": 0.1,
          "place_prob": 0.1,
          "expectancy_score": 0.01,
          "miaomi_score": 1.0,
          "is_value": false,
          "reasoning": "ファーヴェント: 時計面で若干の不安要素あり / 横山武騎手とのコンビネーションに注目 / 直近の仕上がりは安定"
        },
        {
          "horse_number": 7,
          "horse_name": "タイムトゥヘヴン",
          "jockey_name": "田辺",
          "popularity": 10,
          "odds": 9.9,
          "win_prob": 0.1,
          "place_prob": 0.1,
          "expectancy_score": 0.01,
          "miaomi_score": 1.0,
          "is_value": false,
          "reasoning": "タイムトゥヘヴン: 時計面で若干の不安要素あり / 田辺騎手とのコンビネーションに注目 / 直近の仕上がりは安定"
        },
        {
          "horse_number": 12,
          "horse_name": "ダディーズビビッド",
          "jockey_name": "横山和",
          "popularity": 10,
          "odds": 9.9,
          "win_prob": 0.1,
          "place_prob": 0.1,
          "expectancy_score": 0.01,
          "miaomi_score": 1.0,
          "is_value": false,
          "reasoning": "ダディーズビビッド: 時計面で若干の不安要素あり / 横山和騎手とのコンビネーションに注目 / 直近の仕上がりは安定"
        },
        {
          "horse_number": 3,
          "horse_name": "エンペラーズソード",
          "jockey_name": "丹内",
          "popularity": 10,
          "odds": 9.9,
          "win_prob": 0.1,
          "place_prob": 0.0,
          "expectancy_score": 0.0,
          "miaomi_score": 0.0,
          "is_value": false,
          "reasoning": "エンペラーズソード: 時計面で若干の不安要素あり / 丹内騎手とのコンビネーションに注目 / 直近の仕上がりは安定"
        },
        {
          "horse_number": 5,
          "horse_name": "ブエナオンダ",
          "jockey_name": "佐々木",
          "popularity": 10,
          "odds": 9.9,
          "win_prob": 0.1,
          "place_prob": 0.0,
          "expectancy_score": 0.0,
          "miaomi_score": 0.0,
          "is_value": false,
          "reasoning": "ブエナオンダ: 時計面で若干の不安要素あり / 佐々木騎手とのコンビネーションに注目 / 直近の仕上がりは安定"
        },
        {
          "horse_number": 9,
          "horse_name": "エエヤン",
          "jockey_name": "杉原",
          "popularity": 10,
          "odds": 9.9,
          "win_prob": 0.1,
          "place_prob": 0.0,
          "expectancy_score": 0.0,
          "miaomi_score": 0.0,
          "is_value": false,
          "reasoning": "エエヤン: 時計面で若干の不安要素あり / 杉原騎手とのコンビネーションに注目 / 直近の仕上がりは安定"
        },
        {
          "horse_number": 10,
          "horse_name": "ケイアイセナ",
          "jockey_name": "津村",
          "popularity": 10,
          "odds": 9.9,
          "win_prob": 0.1,
          "place_prob": 0.0,
          "expectancy_score": 0.0,
          "miaomi_score": 0.0,
          "is_value": false,
          "reasoning": "ケイアイセナ: 時計面で若干の不安要素あり / 津村騎手とのコンビネーションに注目 / 直近の仕上がりは安定"
        },
        {
          "horse_number": 11,
          "horse_name": "スズハローム",
          "jockey_name": "藤懸",
          "popularity": 10,
          "odds": 9.9,
          "win_prob": 0.1,
          "place_prob": 0.0,
          "expectancy_score": 0.0,
          "miaomi_score": 0.0,
          "is_value": false,
          "reasoning": "スズハローム: 時計面で若干の不安要素あり / 藤懸騎手とのコンビネーションに注目 / 直近の仕上がりは安定"
        },
        {
          "horse_number": 13,
          "horse_name": "イミグラントソング",
          "jockey_name": "石川",
          "popularity": 10,
          "odds": 9.9,
          "win_prob": 0.1,
          "place_prob": 0.0,
          "expectancy_score": 0.0,
          "miaomi_score": 0.0,
          "is_value": false,
          "reasoning": "イミグラントソング: 時計面で若干の不安要素あり / 石川騎手とのコンビネーションに注目 / 直近の仕上がりは安定"
        },
        {
          "horse_number": 14,
          "horse_name": "ジュンブロッサム",
          "jockey_name": "荻野極",
          "popularity": 10,
          "odds": 9.9,
          "win_prob": 0.1,
          "place_prob": 0.0,
          "expectancy_score": 0.0,
          "miaomi_score": 0.0,
          "is_value": false,
          "reasoning": "ジュンブロッサム: 時計面で若干の不安要素あり / 荻野極騎手とのコンビネーションに注目 / 直近の仕上がりは安定"
        },
        {
          "horse_number": 15,
          "horse_name": "シリウスコルト",
          "jockey_name": "三浦",
          "popularity": 10,
          "odds": 9.9,
          "win_prob": 0.1,
          "place_prob": 0.0,
          "expectancy_score": 0.0,
          "miaomi_score": 0.0,
          "is_value": false,
          "reasoning": "シリウスコルト: 時計面で若干の不安要素あり / 三浦騎手とのコンビネーションに注目 / 直近の仕上がりは安定"
        },
        {
          "horse_number": 16,
          "horse_name": "サイルーン",
          "jockey_name": "大野",
          "popularity": 10,
          "odds": 9.9,
          "win_prob": 0.1,
          "place_prob": 0.0,
          "expectancy_score": 0.0,
          "miaomi_score": 0.0,
          "is_value": false,
          "reasoning": "サイルーン: 時計面で若干の不安要素あり / 大野騎手とのコンビネーションに注目 / 直近の仕上がりは安定"
        }
      ]
    },
    {
      "race_id": "202609020311",
      "race_name": "チャーチルダウンズＣ(G3)",
      "is_graded": true,
      "place": "阪神",
      "round": 11,
      "top_pickup": {
        "horse_number": 1,
        "horse_name": "ストームサンダー",
        "jockey_name": "斎藤",
        "popularity": 10,
        "odds": 9.9,
        "features_raw": {
          "umaban": 1.0,
          "wakuban": 1.0,
          "weight_carried": 57.0,
          "horse_weight": 480.0,
          "weight_change": 0.0,
          "age": 3.0,
          "time_index": 49.0,
          "last_3f_index": 49.5,
          "pedigree_index": 24.0,
          "affinity_index": 22.0
        },
        "win_prob": 0.1,
        "place_prob": 0.1,
        "expectancy_score": 0.01,
        "miaomi_score": 1.0,
        "is_value": false,
        "reasoning": "ストームサンダー: 時計面で若干の不安要素あり / 斎藤騎手とのコンビネーションに注目 / 直近の仕上がりは安定"
      },
      "axis_pickup": {
        "horse_number": 2,
        "horse_name": "メイショウソラリス",
        "jockey_name": "角田和",
        "popularity": 10,
        "odds": 9.9,
        "features_raw": {
          "umaban": 2.0,
          "wakuban": 2.0,
          "weight_carried": 57.0,
          "horse_weight": 480.0,
          "weight_change": 0.0,
          "age": 3.0,
          "time_index": 49.0,
          "last_3f_index": 49.5,
          "pedigree_index": 24.0,
          "affinity_index": 22.0
        },
        "win_prob": 0.1,
        "place_prob": 0.1,
        "expectancy_score": 0.01,
        "miaomi_score": 1.0,
        "is_value": false,
        "reasoning": "メイショウソラリス: 時計面で若干の不安要素あり / 角田和騎手とのコンビネーションに注目 / 直近の仕上がりは安定"
      },
      "darkhorse_pickup": {
        "horse_number": 3,
        "horse_name": "リゾートアイランド",
        "jockey_name": "武豊",
        "popularity": 10,
        "odds": 9.9,
        "features_raw": {
          "umaban": 3.0,
          "wakuban": 3.0,
          "weight_carried": 57.0,
          "horse_weight": 480.0,
          "weight_change": 0.0,
          "age": 3.0,
          "time_index": 49.0,
          "last_3f_index": 49.5,
          "pedigree_index": 24.0,
          "affinity_index": 24.0
        },
        "win_prob": 0.1,
        "place_prob": 0.1,
        "expectancy_score": 0.01,
        "miaomi_score": 1.0,
        "is_value": false,
        "reasoning": "リゾートアイランド: 時計面で若干の不安要素あり / 武豊騎手への乗り替わりは明確な勝負気配 / 直近の仕上がりは安定"
      },
      "recommended_bet": "馬連 1 - 2 / ワイド 2 - 3",
      "all_horses": [
        {
          "horse_number": 1,
          "horse_name": "ストームサンダー",
          "jockey_name": "斎藤",
          "popularity": 10,
          "odds": 9.9,
          "win_prob": 0.1,
          "place_prob": 0.1,
          "expectancy_score": 0.01,
          "miaomi_score": 1.0,
          "is_value": false,
          "reasoning": "ストームサンダー: 時計面で若干の不安要素あり / 斎藤騎手とのコンビネーションに注目 / 直近の仕上がりは安定"
        },
        {
          "horse_number": 2,
          "horse_name": "メイショウソラリス",
          "jockey_name": "角田和",
          "popularity": 10,
          "odds": 9.9,
          "win_prob": 0.1,
          "place_prob": 0.1,
          "expectancy_score": 0.01,
          "miaomi_score": 1.0,
          "is_value": false,
          "reasoning": "メイショウソラリス: 時計面で若干の不安要素あり / 角田和騎手とのコンビネーションに注目 / 直近の仕上がりは安定"
        },
        {
          "horse_number": 3,
          "horse_name": "リゾートアイランド",
          "jockey_name": "武豊",
          "popularity": 10,
          "odds": 9.9,
          "win_prob": 0.1,
          "place_prob": 0.1,
          "expectancy_score": 0.01,
          "miaomi_score": 1.0,
          "is_value": false,
          "reasoning": "リゾートアイランド: 時計面で若干の不安要素あり / 武豊騎手への乗り替わりは明確な勝負気配 / 直近の仕上がりは安定"
        },
        {
          "horse_number": 7,
          "horse_name": "サトノセプター",
          "jockey_name": "岩田望",
          "popularity": 10,
          "odds": 9.9,
          "win_prob": 0.1,
          "place_prob": 0.1,
          "expectancy_score": 0.01,
          "miaomi_score": 1.0,
          "is_value": false,
          "reasoning": "サトノセプター: 時計面で若干の不安要素あり / 岩田望騎手とのコンビネーションに注目 / 直近の仕上がりは安定"
        },
        {
          "horse_number": 8,
          "horse_name": "アンドゥーリル",
          "jockey_name": "川田",
          "popularity": 10,
          "odds": 9.9,
          "win_prob": 0.1,
          "place_prob": 0.1,
          "expectancy_score": 0.01,
          "miaomi_score": 1.0,
          "is_value": false,
          "reasoning": "アンドゥーリル: 時計面で若干の不安要素あり / 川田騎手への乗り替わりは明確な勝負気配 / 直近の仕上がりは安定"
        },
        {
          "horse_number": 4,
          "horse_name": "エイシンティザー",
          "jockey_name": "西塚",
          "popularity": 10,
          "odds": 9.9,
          "win_prob": 0.1,
          "place_prob": 0.0,
          "expectancy_score": 0.0,
          "miaomi_score": 0.0,
          "is_value": false,
          "reasoning": "エイシンティザー: 時計面で若干の不安要素あり / 西塚騎手とのコンビネーションに注目 / 直近の仕上がりは安定"
        },
        {
          "horse_number": 6,
          "horse_name": "サンダーストラック",
          "jockey_name": "ルメール",
          "popularity": 10,
          "odds": 9.9,
          "win_prob": 0.1,
          "place_prob": 0.0,
          "expectancy_score": 0.0,
          "miaomi_score": 0.0,
          "is_value": false,
          "reasoning": "サンダーストラック: 時計面で若干の不安要素あり / ルメール騎手への乗り替わりは明確な勝負気配 / 直近の仕上がりは安定"
        },
        {
          "horse_number": 5,
          "horse_name": "シーミハットク",
          "jockey_name": "高杉",
          "popularity": 10,
          "odds": 9.9,
          "win_prob": 0.1,
          "place_prob": 0.0,
          "expectancy_score": 0.0,
          "miaomi_score": 0.0,
          "is_value": false,
          "reasoning": "シーミハットク: 時計面で若干の不安要素あり / 高杉騎手とのコンビネーションに注目 / 直近の仕上がりは安定"
        },
        {
          "horse_number": 9,
          "horse_name": "クールデイトナ",
          "jockey_name": "吉村",
          "popularity": 10,
          "odds": 9.9,
          "win_prob": 0.1,
          "place_prob": 0.0,
          "expectancy_score": 0.0,
          "miaomi_score": 0.0,
          "is_value": false,
          "reasoning": "クールデイトナ: 時計面で若干の不安要素あり / 吉村騎手とのコンビネーションに注目 / 直近の仕上がりは安定"
        },
        {
          "horse_number": 10,
          "horse_name": "バルセシート",
          "jockey_name": "北村友",
          "popularity": 10,
          "odds": 9.9,
          "win_prob": 0.1,
          "place_prob": 0.0,
          "expectancy_score": 0.0,
          "miaomi_score": 0.0,
          "is_value": false,
          "reasoning": "バルセシート: 時計面で若干の不安要素あり / 北村友騎手とのコンビネーションに注目 / 直近の仕上がりは安定"
        },
        {
          "horse_number": 11,
          "horse_name": "ユウファラオ",
          "jockey_name": "松若",
          "popularity": 10,
          "odds": 9.9,
          "win_prob": 0.1,
          "place_prob": 0.0,
          "expectancy_score": 0.0,
          "miaomi_score": 0.0,
          "is_value": false,
          "reasoning": "ユウファラオ: 時計面で若干の不安要素あり / 松若騎手とのコンビネーションに注目 / 直近の仕上がりは安定"
        },
        {
          "horse_number": 12,
          "horse_name": "サーディンラン",
          "jockey_name": "松山",
          "popularity": 10,
          "odds": 9.9,
          "win_prob": 0.1,
          "place_prob": 0.0,
          "expectancy_score": 0.0,
          "miaomi_score": 0.0,
          "is_value": false,
          "reasoning": "サーディンラン: 時計面で若干の不安要素あり / 松山騎手とのコンビネーションに注目 / 直近の仕上がりは安定"
        },
        {
          "horse_number": 13,
          "horse_name": "ファンクション",
          "jockey_name": "鮫島駿",
          "popularity": 10,
          "odds": 9.9,
          "win_prob": 0.1,
          "place_prob": 0.0,
          "expectancy_score": 0.0,
          "miaomi_score": 0.0,
          "is_value": false,
          "reasoning": "ファンクション: 時計面で若干の不安要素あり / 鮫島駿騎手とのコンビネーションに注目 / 直近の仕上がりは安定"
        },
        {
          "horse_number": 14,
          "horse_name": "アスクイキゴミ",
          "jockey_name": "坂井",
          "popularity": 10,
          "odds": 9.9,
          "win_prob": 0.1,
          "place_prob": 0.0,
          "expectancy_score": 0.0,
          "miaomi_score": 0.0,
          "is_value": false,
          "reasoning": "アスクイキゴミ: 時計面で若干の不安要素あり / 坂井騎手への乗り替わりは明確な勝負気配 / 直近の仕上がりは安定"
        }
      ]
    },
    {
      "race_id": "202609020411",
      "race_name": "大阪杯(G1)",
      "is_graded": true,
      "place": "阪神",
      "round": 11,
      "top_pickup": {
        "horse_number": 1,
        "horse_name": "サンストックトン",
        "jockey_name": "高杉",
        "popularity": 10,
        "odds": 9.9,
        "features_raw": {
          "umaban": 1.0,
          "wakuban": 1.0,
          "weight_carried": 58.0,
          "horse_weight": 480.0,
          "weight_change": 0.0,
          "age": 7.0,
          "time_index": 52.0,
          "last_3f_index": 51.0,
          "pedigree_index": 22.0,
          "affinity_index": 20.0
        },
        "win_prob": 0.1,
        "place_prob": 0.1,
        "expectancy_score": 0.01,
        "miaomi_score": 1.0,
        "is_value": false,
        "reasoning": "サンストックトン: 時計面で若干の不安要素あり / 高杉騎手とのコンビネーションに注目 / 直近の仕上がりは安定"
      },
      "axis_pickup": {
        "horse_number": 8,
        "horse_name": "エコロヴァルツ",
        "jockey_name": "浜中",
        "popularity": 10,
        "odds": 9.9,
        "features_raw": {
          "umaban": 8.0,
          "wakuban": 5.0,
          "weight_carried": 58.0,
          "horse_weight": 480.0,
          "weight_change": 0.0,
          "age": 5.0,
          "time_index": 54.0,
          "last_3f_index": 52.0,
          "pedigree_index": 24.0,
          "affinity_index": 23.0
        },
        "win_prob": 0.1,
        "place_prob": 0.6,
        "expectancy_score": 0.06,
        "miaomi_score": 6.0,
        "is_value": false,
        "reasoning": "エコロヴァルツ: 時計面で若干の不安要素あり / 浜中騎手とのコンビネーションに注目 / 直近の仕上がりは安定"
      },
      "darkhorse_pickup": {
        "horse_number": 2,
        "horse_name": "マテンロウレオ",
        "jockey_name": "横山典",
        "popularity": 10,
        "odds": 9.9,
        "features_raw": {
          "umaban": 2.0,
          "wakuban": 2.0,
          "weight_carried": 58.0,
          "horse_weight": 480.0,
          "weight_change": 0.0,
          "age": 7.0,
          "time_index": 53.0,
          "last_3f_index": 51.5,
          "pedigree_index": 23.0,
          "affinity_index": 25.0
        },
        "win_prob": 0.1,
        "place_prob": 0.1,
        "expectancy_score": 0.01,
        "miaomi_score": 1.0,
        "is_value": false,
        "reasoning": "マテンロウレオ: 時計面で若干の不安要素あり / 横山典騎手とのコンビネーションに注目 / 直近の仕上がりは安定"
      },
      "recommended_bet": "馬連 1 - 8 / ワイド 8 - 2",
      "all_horses": [
        {
          "horse_number": 8,
          "horse_name": "エコロヴァルツ",
          "jockey_name": "浜中",
          "popularity": 10,
          "odds": 9.9,
          "win_prob": 0.1,
          "place_prob": 0.6,
          "expectancy_score": 0.06,
          "miaomi_score": 6.0,
          "is_value": false,
          "reasoning": "エコロヴァルツ: 時計面で若干の不安要素あり / 浜中騎手とのコンビネーションに注目 / 直近の仕上がりは安定"
        },
        {
          "horse_number": 2,
          "horse_name": "マテンロウレオ",
          "jockey_name": "横山典",
          "popularity": 10,
          "odds": 9.9,
          "win_prob": 0.1,
          "place_prob": 0.1,
          "expectancy_score": 0.01,
          "miaomi_score": 1.0,
          "is_value": false,
          "reasoning": "マテンロウレオ: 時計面で若干の不安要素あり / 横山典騎手とのコンビネーションに注目 / 直近の仕上がりは安定"
        },
        {
          "horse_number": 1,
          "horse_name": "サンストックトン",
          "jockey_name": "高杉",
          "popularity": 10,
          "odds": 9.9,
          "win_prob": 0.1,
          "place_prob": 0.1,
          "expectancy_score": 0.01,
          "miaomi_score": 1.0,
          "is_value": false,
          "reasoning": "サンストックトン: 時計面で若干の不安要素あり / 高杉騎手とのコンビネーションに注目 / 直近の仕上がりは安定"
        },
        {
          "horse_number": 9,
          "horse_name": "ヨーホーレイク",
          "jockey_name": "西村淳",
          "popularity": 10,
          "odds": 9.9,
          "win_prob": 0.1,
          "place_prob": 0.1,
          "expectancy_score": 0.01,
          "miaomi_score": 1.0,
          "is_value": false,
          "reasoning": "ヨーホーレイク: 時計面で若干の不安要素あり / 西村淳騎手とのコンビネーションに注目 / 直近の仕上がりは安定"
        },
        {
          "horse_number": 3,
          "horse_name": "セイウンハーデス",
          "jockey_name": "幸",
          "popularity": 10,
          "odds": 9.9,
          "win_prob": 0.1,
          "place_prob": 0.1,
          "expectancy_score": 0.01,
          "miaomi_score": 1.0,
          "is_value": false,
          "reasoning": "セイウンハーデス: 時計面で若干の不安要素あり / 幸騎手とのコンビネーションに注目 / 直近の仕上がりは安定"
        },
        {
          "horse_number": 4,
          "horse_name": "ダノンデサイル",
          "jockey_name": "坂井",
          "popularity": 10,
          "odds": 9.9,
          "win_prob": 0.1,
          "place_prob": 0.0,
          "expectancy_score": 0.0,
          "miaomi_score": 0.0,
          "is_value": false,
          "reasoning": "ダノンデサイル: 時計面で若干の不安要素あり / 坂井騎手への乗り替わりは明確な勝負気配 / 直近の仕上がりは安定"
        },
        {
          "horse_number": 5,
          "horse_name": "ショウヘイ",
          "jockey_name": "川田",
          "popularity": 10,
          "odds": 9.9,
          "win_prob": 0.1,
          "place_prob": 0.0,
          "expectancy_score": 0.0,
          "miaomi_score": 0.0,
          "is_value": false,
          "reasoning": "ショウヘイ: 時計面で若干の不安要素あり / 川田騎手への乗り替わりは明確な勝負気配 / 直近の仕上がりは安定"
        },
        {
          "horse_number": 7,
          "horse_name": "エコロディノス",
          "jockey_name": "池添",
          "popularity": 10,
          "odds": 9.9,
          "win_prob": 0.1,
          "place_prob": 0.0,
          "expectancy_score": 0.0,
          "miaomi_score": 0.0,
          "is_value": false,
          "reasoning": "エコロディノス: 時計面で若干の不安要素あり / 池添騎手とのコンビネーションに注目 / 直近の仕上がりは安定"
        },
        {
          "horse_number": 6,
          "horse_name": "メイショウタバル",
          "jockey_name": "武豊",
          "popularity": 10,
          "odds": 9.9,
          "win_prob": 0.1,
          "place_prob": 0.0,
          "expectancy_score": 0.0,
          "miaomi_score": 0.0,
          "is_value": false,
          "reasoning": "メイショウタバル: 時計面で若干の不安要素あり / 武豊騎手への乗り替わりは明確な勝負気配 / 直近の仕上がりは安定"
        },
        {
          "horse_number": 10,
          "horse_name": "ボルドグフーシュ",
          "jockey_name": "松山",
          "popularity": 10,
          "odds": 9.9,
          "win_prob": 0.1,
          "place_prob": 0.0,
          "expectancy_score": 0.0,
          "miaomi_score": 0.0,
          "is_value": false,
          "reasoning": "ボルドグフーシュ: 時計面で若干の不安要素あり / 松山騎手とのコンビネーションに注目 / 直近の仕上がりは安定"
        },
        {
          "horse_number": 11,
          "horse_name": "デビットバローズ",
          "jockey_name": "岩田望",
          "popularity": 10,
          "odds": 9.9,
          "win_prob": 0.1,
          "place_prob": 0.0,
          "expectancy_score": 0.0,
          "miaomi_score": 0.0,
          "is_value": false,
          "reasoning": "デビットバローズ: 時計面で若干の不安要素あり / 岩田望騎手とのコンビネーションに注目 / 直近の仕上がりは安定"
        },
        {
          "horse_number": 12,
          "horse_name": "レーベンスティール",
          "jockey_name": "ルメール",
          "popularity": 10,
          "odds": 9.9,
          "win_prob": 0.1,
          "place_prob": 0.0,
          "expectancy_score": 0.0,
          "miaomi_score": 0.0,
          "is_value": false,
          "reasoning": "レーベンスティール: 時計面で若干の不安要素あり / ルメール騎手への乗り替わりは明確な勝負気配 / 直近の仕上がりは安定"
        },
        {
          "horse_number": 13,
          "horse_name": "ファウストラーゼン",
          "jockey_name": "岩田康",
          "popularity": 10,
          "odds": 9.9,
          "win_prob": 0.1,
          "place_prob": 0.0,
          "expectancy_score": 0.0,
          "miaomi_score": 0.0,
          "is_value": false,
          "reasoning": "ファウストラーゼン: 時計面で若干の不安要素あり / 岩田康騎手とのコンビネーションに注目 / 直近の仕上がりは安定"
        },
        {
          "horse_number": 14,
          "horse_name": "タガノデュード",
          "jockey_name": "古川吉",
          "popularity": 10,
          "odds": 9.9,
          "win_prob": 0.1,
          "place_prob": 0.0,
          "expectancy_score": 0.0,
          "miaomi_score": 0.0,
          "is_value": false,
          "reasoning": "タガノデュード: 時計面で若干の不安要素あり / 古川吉騎手とのコンビネーションに注目 / 直近の仕上がりは安定"
        },
        {
          "horse_number": 15,
          "horse_name": "クロワデュノール",
          "jockey_name": "北村友",
          "popularity": 10,
          "odds": 9.9,
          "win_prob": 0.1,
          "place_prob": 0.0,
          "expectancy_score": 0.0,
          "miaomi_score": 0.0,
          "is_value": false,
          "reasoning": "クロワデュノール: 時計面で若干の不安要素あり / 北村友騎手とのコンビネーションに注目 / 直近の仕上がりは安定"
        }
      ]
    }
  ],
  "value_picks": []
}